Metadata-Version: 1.0
Name: CI-CD-SergiCastilloprueba
Version: 0.1.0
Summary: KeepCoding
Home-page: https://github.com/sergicastin/CI-CD-SergiCastillo
Author: Sergi Castillo
Author-email: UNKNOWN
License: UNKNOWN
Platform: UNKNOWN
